chunky3d/__init__.py
chunky3d/_version.py
chunky3d/chunk.py
chunky3d/chunky.py
chunky3d/helpers.py
chunky3d/k3d_connector.py
chunky3d/multiprocesses.py
chunky3d/sparse_func.py
chunky3d/vtk_utils.py
chunky3d/geometry/__init__.py
chunky3d/geometry/extract.py
test/__init__.py
test/test_helpers.py
test/test_sparse.py
test/test_sparse_func.py
chunky3d-0.1.15.dist-info/LICENSE
chunky3d-0.1.15.dist-info/METADATA
chunky3d-0.1.15.dist-info/WHEEL
chunky3d-0.1.15.dist-info/top_level.txt
chunky3d-0.1.15.dist-info/RECORD
