Metadata-Version: 2.2
Name: chunky3d
Version: 0.1.15
Summary: A 3D array-like NumPy-based data structure for large sparsely-populated volumes
License: MIT
Project-URL: Source, https://github.com/K3D-tools/chunky3d
Project-URL: Tracker, https://github.com/K3D-tools/chunky3d/issues
Keywords: 3d,array,chunked,sparse
Classifier: Development Status :: 4 - Beta
Classifier: License :: OSI Approved :: MIT License
Classifier: Intended Audience :: Developers
Classifier: Intended Audience :: Science/Research
Classifier: Intended Audience :: Healthcare Industry
Classifier: Topic :: Multimedia :: Graphics :: 3D Modeling
Classifier: Topic :: Scientific/Engineering :: Medical Science Apps.
Classifier: Programming Language :: Python :: 3
Classifier: Programming Language :: Python :: 3.8
Classifier: Programming Language :: Python :: 3.9
Classifier: Programming Language :: Python :: 3.10
License-File: LICENSE
Requires-Dist: dill
Requires-Dist: msgpack
Requires-Dist: msgpack_numpy
Requires-Dist: numba
Requires-Dist: numpy
Requires-Dist: psutil
Requires-Dist: scipy
Requires-Dist: scikit-image
Provides-Extra: all
Requires-Dist: itk; extra == "all"
Requires-Dist: itk-thickness3d; extra == "all"
Requires-Dist: networkx; extra == "all"
Requires-Dist: scikit-image; extra == "all"
Requires-Dist: SimpleITK; extra == "all"
Requires-Dist: vtk; extra == "all"
Dynamic: classifier
Dynamic: description
Dynamic: description-content-type
Dynamic: keywords
Dynamic: license
Dynamic: project-url
Dynamic: provides-extra
Dynamic: requires-dist
Dynamic: summary
